diagnostipy/__init__.py
diagnostipy/core/__init__.py
diagnostipy/core/evaluator.py
diagnostipy/core/models/__init__.py
diagnostipy/core/models/diagnosis.py
diagnostipy/core/models/evaluation.py
diagnostipy/core/models/symptom_rule.py
diagnostipy/core/ruleset.py
diagnostipy/core/typing.py
diagnostipy/utils/__init__.py
diagnostipy/utils/enums.py
diagnostipy/utils/scoring/__init__.py
diagnostipy/utils/scoring/confidence_functions.py
diagnostipy/utils/scoring/evaluation_functions.py
diagnostipy/utils/scoring/helpers.py
diagnostipy/utils/scoring/types.py
diagnostipy-0.1.2.dist-info/LICENSE
diagnostipy-0.1.2.dist-info/METADATA
diagnostipy-0.1.2.dist-info/WHEEL
diagnostipy-0.1.2.dist-info/RECORD
