Metadata-Version: 2.1
Name: diagnostipy
Version: 0.1.2
Summary: 
License: MIT
Author: Michał Grela
Author-email: michal.grela@themomentum.ai
Requires-Python: >=3.10,<4.0
Classifier: License :: OSI Approved :: MIT License
Classifier: Programming Language :: Python :: 3
Classifier: Programming Language :: Python :: 3.10
Classifier: Programming Language :: Python :: 3.11
Classifier: Programming Language :: Python :: 3.12
Requires-Dist: numpy (>=2.1.3,<3.0.0)
Requires-Dist: pydantic (>=2.10.1,<3.0.0)
